kats/__init__.py
kats/consts.py
kats/compat/__init__.py
kats/compat/compat.py
kats/compat/pandas.py
kats/compat/statsmodels.py
kats/data/__init__.py
kats/data/utils.py
kats/detectors/__init__.py
kats/detectors/bocpd.py
kats/detectors/bocpd_model.py
kats/detectors/changepoint_evaluator.py
kats/detectors/cusum_detection.py
kats/detectors/cusum_model.py
kats/detectors/detector.py
kats/detectors/detector_benchmark.py
kats/detectors/detector_consts.py
kats/detectors/dtwcpd.py
kats/detectors/hourly_ratio_detection.py
kats/detectors/outlier.py
kats/detectors/outlier_detector.py
kats/detectors/prophet_detector.py
kats/detectors/residual_translation.py
kats/detectors/robust_stat_detection.py
kats/detectors/seasonality.py
kats/detectors/stat_sig_detector.py
kats/detectors/threshold_detector.py
kats/detectors/trend_mk.py
kats/detectors/meta_learning/__init__.py
kats/detectors/meta_learning/exceptions.py
kats/detectors/meta_learning/hpt_tuning.py
kats/detectors/meta_learning/metalearning_detection_model.py
kats/detectors/meta_learning/synth_metadata_reader.py
kats/graphics/__init__.py
kats/graphics/plots.py
kats/models/__init__.py
kats/models/arima.py
kats/models/bayesian_var.py
kats/models/harmonic_regression.py
kats/models/holtwinters.py
kats/models/linear_model.py
kats/models/lstm.py
kats/models/model.py
kats/models/prophet.py
kats/models/quadratic_model.py
kats/models/sarima.py
kats/models/stlf.py
kats/models/theta.py
kats/models/var.py
kats/models/ensemble/__init__.py
kats/models/ensemble/ensemble.py
kats/models/ensemble/kats_ensemble.py
kats/models/ensemble/median_ensemble.py
kats/models/ensemble/weighted_avg_ensemble.py
kats/models/globalmodel/__init__.py
kats/models/globalmodel/backtester.py
kats/models/globalmodel/data_processor.py
kats/models/globalmodel/ensemble.py
kats/models/globalmodel/model.py
kats/models/globalmodel/serialize.py
kats/models/globalmodel/utils.py
kats/models/metalearner/__init__.py
kats/models/metalearner/get_metadata.py
kats-0.2.0.dist-info/LICENSE
kats-0.2.0.dist-info/METADATA
kats-0.2.0.dist-info/WHEEL
kats-0.2.0.dist-info/top_level.txt
kats-0.2.0.dist-info/RECORD
