Metadata-Version: 2.1
Name: kats
Version: 0.2.0
Summary: kats: kit to analyze time series
Home-page: https://github.com/facebookresearch/Kats
Download-URL: https://github.com/facebookresearch/Kats/archive/refs/tags/v0.1.tar.gz
Author: facebook
Author-email: iamxiaodong@fb.com
License: MIT
Keywords: time series,forecasting,anomaly detection,tsfeatures,temporal embedding
Platform: UNKNOWN
Classifier: Development Status :: 3 - Alpha
Classifier: Intended Audience :: Science/Research
Classifier: Topic :: Scientific/Engineering :: Artificial Intelligence
Classifier: License :: OSI Approved :: MIT License
Classifier: Programming Language :: Python :: 3.7
Classifier: Programming Language :: Python :: 3.8
License-File: LICENSE
Requires-Dist: attrs (>=21.2.0)
Requires-Dist: deprecated (>=1.2.12)
Requires-Dist: matplotlib (>=2.0.0)
Requires-Dist: numpy (<1.22,>=1.21)
Requires-Dist: pandas (<=1.3.5,>=1.0.4)
Requires-Dist: python-dateutil (>=2.8.0)
Requires-Dist: pystan (==2.19.1.1)
Requires-Dist: fbprophet (==0.7.1)
Requires-Dist: scikit-learn (>=0.24.2)
Requires-Dist: scipy (<1.8.0)
Requires-Dist: seaborn (>=0.11.1)
Requires-Dist: setuptools-git (>=1.2)
Requires-Dist: statsmodels (==0.12.2)
Requires-Dist: LunarCalendar (>=0.0.9)
Requires-Dist: ax-platform (==0.2.4)
Requires-Dist: gpytorch
Requires-Dist: holidays (>=0.10.2)
Requires-Dist: numba (>=0.52.0)
Requires-Dist: parameterized (>=0.8.1)
Requires-Dist: plotly (>=2.2.1)
Requires-Dist: pymannkendall (>=1.4.1)
Requires-Dist: pytest-mpl (>=0.12)
Requires-Dist: torch
Requires-Dist: tqdm (>=4.36.1)
Requires-Dist: importlib-metadata ; python_version < "3.8"
Requires-Dist: typing-extensions ; python_version < "3.8"
